competitivetracker/__init__.py
competitivetracker/base.py
competitivetracker/core.py
competitivetracker/domain_info.py
competitivetracker/exceptions.py
competitivetracker/intelligence.py
competitivetracker/overlaps.py
competitivetracker/ping.py
competitivetracker/search.py
competitivetracker-1.1.0.dist-info/METADATA
competitivetracker-1.1.0.dist-info/WHEEL
competitivetracker-1.1.0.dist-info/top_level.txt
competitivetracker-1.1.0.dist-info/RECORD
